drvi/DRhtml.cp310-win_amd64.pyd
drvi/__init__.py
drvi/drColorWin.cp310-win_amd64.pyd
drvi/drHelp.cp310-win_amd64.pyd
drvi/drffmpeg.cp310-win_amd64.pyd
drvi/drviAppendPath.cp310-win_amd64.pyd
drvi/drviAudio.cp310-win_amd64.pyd
drvi/drviBreadBoard.cp310-win_amd64.pyd
drvi/drviCodeGenerator.cp310-win_amd64.pyd
drvi/drviControlls.cp310-win_amd64.pyd
drvi/drviDSP.cp310-win_amd64.pyd
drvi/drviExample.cp310-win_amd64.pyd
drvi/drviNet.cp310-win_amd64.pyd
drvi/drviSerial.cp310-win_amd64.pyd
drvi/drviSimpleAudio.cp310-win_amd64.pyd
drvi/vibesystem.cp310-win_amd64.pyd
drvi-0.0.10.dist-info/LICENSE.txt
drvi-0.0.10.dist-info/METADATA
drvi-0.0.10.dist-info/WHEEL
drvi-0.0.10.dist-info/top_level.txt
drvi-0.0.10.dist-info/RECORD
