Metadata-Version: 2.1
Name: drvi
Version: 0.0.10
Summary: DRVI
Author: Lingsong HE
Author-email: <helingsong@hust.edu.cn>
Keywords: python,app designer,virtual instrument
Classifier: Development Status :: 3 - Alpha
Classifier: Intended Audience :: Education
Classifier: Programming Language :: Python :: 3
Classifier: License :: OSI Approved :: MIT License
Classifier: Operating System :: Microsoft :: Windows
Requires-Python: >=3.10
License-File: LICENSE.txt
